odoo/addons/invader_payment_adyen_sepa/README.rst
odoo/addons/invader_payment_adyen_sepa/__init__.py
odoo/addons/invader_payment_adyen_sepa/__manifest__.py
odoo/addons/invader_payment_adyen_sepa/data/ir_cron.xml
odoo/addons/invader_payment_adyen_sepa/i18n/invader_payment_adyen_sepa.pot
odoo/addons/invader_payment_adyen_sepa/models/__init__.py
odoo/addons/invader_payment_adyen_sepa/models/account_payment_line.py
odoo/addons/invader_payment_adyen_sepa/models/account_payment_method.py
odoo/addons/invader_payment_adyen_sepa/models/account_payment_order.py
odoo/addons/invader_payment_adyen_sepa/models/invader_payable.py
odoo/addons/invader_payment_adyen_sepa/models/payment_transaction.py
odoo/addons/invader_payment_adyen_sepa/readme/CONTRIBUTORS.rst
odoo/addons/invader_payment_adyen_sepa/readme/DESCRIPTION.rst
odoo/addons/invader_payment_adyen_sepa/readme/HISTORY.rst
odoo/addons/invader_payment_adyen_sepa/static/description/index.html
odoo/addons/invader_payment_adyen_sepa/tests/__init__.py
odoo/addons/invader_payment_adyen_sepa/tests/common.py
odoo/addons/invader_payment_adyen_sepa/tests/test_account_payment_order.py
odoo/addons/invader_payment_adyen_sepa/views/account_payment_method.xml
odoo/addons/invader_payment_adyen_sepa/views/account_payment_order.xml
odoo14_addon_invader_payment_adyen_sepa-14.0.1.2.0.dist-info/METADATA
odoo14_addon_invader_payment_adyen_sepa-14.0.1.2.0.dist-info/WHEEL
odoo14_addon_invader_payment_adyen_sepa-14.0.1.2.0.dist-info/top_level.txt
odoo14_addon_invader_payment_adyen_sepa-14.0.1.2.0.dist-info/RECORD
