Metadata-Version: 2.1
Name: odoo14-addon-invader-payment-adyen-sepa
Version: 14.0.1.2.0
Summary: Manage SEPA payment by Adyen
Home-page: https://github.com/shopinvader/odoo-shopinvader-payment
Author: ACSONE SA/NV,Odoo Community Association (OCA)
Author-email: support@odoo-community.org
License: AGPL-3
Platform: UNKNOWN
Classifier: Programming Language :: Python
Classifier: Framework :: Odoo
Classifier: Framework :: Odoo :: 14.0
Classifier: License :: OSI Approved :: GNU Affero General Public License v3
Requires-Python: >=3.6
Requires-Dist: Adyen
Requires-Dist: odoo14-addon-account-banking-sepa-direct-debit
Requires-Dist: odoo14-addon-base-technical-user
Requires-Dist: odoo14-addon-invader-payment-adyen
Requires-Dist: odoo14-addon-queue-job
Requires-Dist: odoo <14.1dev,>=14.0a
